wago/__init__.py
wago/client.py
wago/models.py
wago_api-0.0.1.dist-info/LICENSE
wago_api-0.0.1.dist-info/METADATA
wago_api-0.0.1.dist-info/WHEEL
wago_api-0.0.1.dist-info/top_level.txt
wago_api-0.0.1.dist-info/RECORD
