Metadata-Version: 2.1
Name: wago-api
Version: 0.0.1
Summary: An async API wrapper for wago.tools
Author-email: Ghostopheles <ghost@ghst.tools>
License: This is free and unencumbered software released into the public domain.
Project-URL: Homepage, https://github.com/Ghostopheles/py-wago-api
Project-URL: Repository, https://github.com/Ghostopheles/py-wago-api.git
Project-URL: Issues, https://github.com/Ghostopheles/py-wago-api/issues
Classifier: Development Status :: 3 - Alpha
Classifier: Intended Audience :: Developers
Classifier: License :: Public Domain
Classifier: Programming Language :: Python :: 3
Classifier: Programming Language :: Python :: 3 :: Only
Classifier: Programming Language :: Python :: 3.13
Classifier: Programming Language :: Python :: 3.12
Classifier: Programming Language :: Python :: 3.11
Requires-Python: >=3.11
License-File: LICENSE
Requires-Dist: httpx[http2]
